{
  "order-book": {
    "market": "BTC",
    "currency": "BRL",
    "bid": [
      {
        "price": 1000,
        "order_amount": 1,
        "order_value": 1000,
        "converted_from": "BRL",
        "timestamp": 1607692433
      },
      {
        "price": 2000,
        "order_amount": 1,
        "order_value": 2000,
        "converted_from": "BRL",
        "timestamp": 1607693889
      }
    ],
    "ask": [
      {
        "price": 107365.87,
        "order_amount": 1,
        "order_value": 107365.87,
        "converted_from": "BRL",
        "timestamp": 1607699999
      },
      {
        "price": 107377.46,
        "order_amount": 0.5,
        "order_value": 53668.73,
        "converted_from": "BRL",
        "timestamp": 1607699999
      }
    ]
  }
}
